[
  {
    "id": "P00004",
    "nombre": "Ac Milan 2006 Local Retro",
    "descripcion": "Camiseta retro AC Milan 2006 versión local",
    "precio": 45,
    "stock": 25,
    "categoryId": "C00004",
    "categoria": "Fútbol",
    "imagen": "/assets/images/ac-milan-2006-local-retro.webp",
    "createdAt": "2026-01-08T06:27:22.000Z"
  },
  {
    "id": "P00005",
    "nombre": "Ac Milan 2006 Visitante Retro",
    "descripcion": "Camiseta retro AC Milan 2006 versión visitante",
    "precio": 45,
    "stock": 25,
    "categoryId": "C00004",
    "categoria": "Fútbol",
    "imagen": "/assets/images/ac-milan-2006-visitante-retro.webp",
    "createdAt": "2026-01-08T06:27:22.000Z"
  },
  {
    "id": "P00006",
    "nombre": "Ac Milan 2025 Away",
    "descripcion": "Camiseta AC Milan 2025 versión visitante",
    "precio": 60,
    "stock": 30,
    "categoryId": "C00004",
    "categoria": "Fútbol",
    "imagen": "/assets/images/ac-milan-2025-away.webp",
    "createdAt": "2026-01-08T06:27:22.000Z"
  },
  {
    "id": "P00007",
    "nombre": "Ac Milan 2025 Local",
    "descripcion": "Camiseta AC Milan 2025 versión local",
    "precio": 60,
    "stock": 30,
    "categoryId": "C00004",
    "categoria": "Fútbol",
    "imagen": "/assets/images/ac-milan-2025-local.webp",
    "createdAt": "2026-01-08T06:27:22.000Z"
  },
  {
    "id": "P00008",
    "nombre": "Alemania 2024 Home",
    "descripcion": "Camiseta selección Alemania 2024 versión local",
    "precio": 45,
    "stock": 25,
    "categoryId": "C00004",
    "categoria": "Fútbol",
    "imagen": "/assets/images/alemania-2024-home.webp",
    "createdAt": "2026-01-08T06:27:22.000Z"
  },
  {
    "id": "P00009",
    "nombre": "Argentina 1999 Visitante Retro",
    "descripcion": "Camiseta retro selección Argentina 1999 visitante",
    "precio": 45,
    "stock": 25,
    "categoryId": "C00004",
    "categoria": "Fútbol",
    "imagen": "/assets/images/argentina-1999-visitante-retro.webp",
    "createdAt": "2026-01-08T06:27:22.000Z"
  },
  {
    "id": "P00010",
    "nombre": "Argentina 2005 Local Retro",
    "descripcion": "Camiseta retro selección Argentina 2005 local",
    "precio": 45,
    "stock": 25,
    "categoryId": "C00004",
    "categoria": "Fútbol",
    "imagen": "/assets/images/argentina-2005-local-retro.webp",
    "createdAt": "2026-01-08T06:27:22.000Z"
  },
  {
    "id": "P00011",
    "nombre": "Argentina 2026 Local",
    "descripcion": "Camiseta selección Argentina 2026 versión local",
    "precio": 60,
    "stock": 30,
    "categoryId": "C00004",
    "categoria": "Fútbol",
    "imagen": "/assets/images/argentina-2026-local.webp",
    "createdAt": "2026-01-08T06:27:22.000Z"
  },
  {
    "id": "P00012",
    "nombre": "Arsenal 2025 Away",
    "descripcion": "Camiseta Arsenal 2025 versión visitante",
    "precio": 60,
    "stock": 30,
    "categoryId": "C00004",
    "categoria": "Fútbol",
    "imagen": "/assets/images/arsenal-2025-away.webp",
    "createdAt": "2026-01-08T06:27:22.000Z"
  },
  {
    "id": "P00013",
    "nombre": "Barcelona 1987 Local Retro",
    "descripcion": "Camiseta retro FC Barcelona 1987 versión local",
    "precio": 45,
    "stock": 25,
    "categoryId": "C00004",
    "categoria": "Fútbol",
    "imagen": "/assets/images/barcelona-1987-local-retro.webp",
    "createdAt": "2026-01-08T06:27:22.000Z"
  },
  {
    "id": "P00014",
    "nombre": "Barcelona 2026 Local",
    "descripcion": "Camiseta FC Barcelona 2026 versión local",
    "precio": 60,
    "stock": 30,
    "categoryId": "C00004",
    "categoria": "Fútbol",
    "imagen": "/assets/images/barcelona-2026-local.webp",
    "createdAt": "2026-01-08T06:27:22.000Z"
  },
  {
    "id": "P00015",
    "nombre": "Bayern Munich 2026 Away",
    "descripcion": "Camiseta Bayern Munich 2026 versión visitante",
    "precio": 60,
    "stock": 30,
    "categoryId": "C00004",
    "categoria": "Fútbol",
    "imagen": "/assets/images/bayern-munich-2026-away.webp",
    "createdAt": "2026-01-08T06:27:22.000Z"
  },
  {
    "id": "P00016",
    "nombre": "Bayern Munich 2026 Local",
    "descripcion": "Camiseta Bayern Munich 2026 versión local",
    "precio": 60,
    "stock": 30,
    "categoryId": "C00004",
    "categoria": "Fútbol",
    "imagen": "/assets/images/bayern-munich-2026-local.webp",
    "createdAt": "2026-01-08T06:27:22.000Z"
  },
  {
    "id": "P00017",
    "nombre": "Boca Jr 1995 Local Retro",
    "descripcion": "Camiseta retro Boca Juniors 1995 versión local",
    "precio": 45,
    "stock": 25,
    "categoryId": "C00004",
    "categoria": "Fútbol",
    "imagen": "/assets/images/boca-jr-1995-local-retro.webp",
    "createdAt": "2026-01-08T06:27:22.000Z"
  },
  {
    "id": "P00018",
    "nombre": "Borussia 2025 Home",
    "descripcion": "Camiseta Borussia Dortmund 2025 versión local",
    "precio": 60,
    "stock": 30,
    "categoryId": "C00004",
    "categoria": "Fútbol",
    "imagen": "/assets/images/borussia-2025-home.webp",
    "createdAt": "2026-01-08T06:27:22.000Z"
  },
  {
    "id": "P00019",
    "nombre": "Brasil 2008 Local Retro",
    "descripcion": "Camiseta retro selección Brasil 2008 local",
    "precio": 45,
    "stock": 25,
    "categoryId": "C00004",
    "categoria": "Fútbol",
    "imagen": "/assets/images/brasil-2008-local-retro.webp",
    "createdAt": "2026-01-08T06:27:22.000Z"
  },
  {
    "id": "P00020",
    "nombre": "Brasil 2009 Total 90 Retro",
    "descripcion": "Camiseta retro selección Brasil 2009 Total 90",
    "precio": 45,
    "stock": 25,
    "categoryId": "C00004",
    "categoria": "Fútbol",
    "imagen": "/assets/images/brasil-2009-total-90-retro.webp",
    "createdAt": "2026-01-08T06:27:22.000Z"
  },
  {
    "id": "P00021",
    "nombre": "Brasil 2024 Local",
    "descripcion": "Camiseta selección Brasil 2024 versión local",
    "precio": 45,
    "stock": 25,
    "categoryId": "C00004",
    "categoria": "Fútbol",
    "imagen": "/assets/images/brasil-2024-local.webp",
    "createdAt": "2026-01-08T06:27:22.000Z"
  },
  {
    "id": "P00023",
    "nombre": "Chelsea 2026 Local",
    "descripcion": "Camiseta Chelsea 2026 versión local",
    "precio": 60,
    "stock": 30,
    "categoryId": "C00004",
    "categoria": "Fútbol",
    "imagen": "/assets/images/chelsea-2026-local.webp",
    "createdAt": "2026-01-08T06:27:22.000Z"
  },
  {
    "id": "P00025",
    "nombre": "Club Brujas 2025 Home",
    "descripcion": "Camiseta Club Brujas 2025 versión local",
    "precio": 60,
    "stock": 30,
    "categoryId": "C00004",
    "categoria": "Fútbol",
    "imagen": "/assets/images/club-brujas-2025-home.webp",
    "createdAt": "2026-01-08T06:27:22.000Z"
  },
  {
    "id": "P00027",
    "nombre": "Emelec 2025 Home Ecuador",
    "descripcion": "Camiseta Emelec 2025 versión local",
    "precio": 60,
    "stock": 30,
    "categoryId": "C00004",
    "categoria": "Fútbol",
    "imagen": "/assets/images/emelec-2025-home-ecuador.webp",
    "createdAt": "2026-01-08T06:27:22.000Z"
  },
  {
    "id": "P00029",
    "nombre": "Fc Barcelona 1999 Local Retro",
    "descripcion": "Camiseta retro FC Barcelona 1999 versión local",
    "precio": 45,
    "stock": 25,
    "categoryId": "C00004",
    "categoria": "Fútbol",
    "imagen": "/assets/images/fc-barcelona-1999-local-retro.webp",
    "createdAt": "2026-01-08T06:27:22.000Z"
  },
  {
    "id": "P00030",
    "nombre": "Fc Barcelona 2015 Local Retro",
    "descripcion": "Camiseta retro FC Barcelona 2015 versión local",
    "precio": 45,
    "stock": 25,
    "categoryId": "C00004",
    "categoria": "Fútbol",
    "imagen": "/assets/images/fc-barcelona-2015-local-retro.webp",
    "createdAt": "2026-01-08T06:27:22.000Z"
  },
  {
    "id": "P00031",
    "nombre": "Francia 2025 Away",
    "descripcion": "Camiseta selección Francia 2025 versión visitante",
    "precio": 60,
    "stock": 30,
    "categoryId": "C00004",
    "categoria": "Fútbol",
    "imagen": "/assets/images/francia-2025-away.webp",
    "createdAt": "2026-01-08T06:27:22.000Z"
  },
  {
    "id": "P00032",
    "nombre": "Idv 2025 Home",
    "descripcion": "Camiseta Independiente del Valle 2025 versión local",
    "precio": 60,
    "stock": 30,
    "categoryId": "C00004",
    "categoria": "Fútbol",
    "imagen": "/assets/images/idv-2025-home.webp",
    "createdAt": "2026-01-08T06:27:22.000Z"
  },
  {
    "id": "P00033",
    "nombre": "Inglaterra 2025 Home",
    "descripcion": "Camiseta selección Inglaterra 2025 versión local",
    "precio": 60,
    "stock": 30,
    "categoryId": "C00004",
    "categoria": "Fútbol",
    "imagen": "/assets/images/inglaterra-2025-home.webp",
    "createdAt": "2026-01-08T06:27:22.000Z"
  },
  {
    "id": "P00034",
    "nombre": "Inter Miami 2025 Local",
    "descripcion": "Camiseta Inter Miami 2025 versión local",
    "precio": 60,
    "stock": 30,
    "categoryId": "C00004",
    "categoria": "Fútbol",
    "imagen": "/assets/images/inter-miami-2025-local.webp",
    "createdAt": "2026-01-08T06:27:22.000Z"
  },
  {
    "id": "P00035",
    "nombre": "Inter Miami Home 2025",
    "descripcion": "Camiseta Inter Miami 2025 versión home alternativa",
    "precio": 60,
    "stock": 30,
    "categoryId": "C00004",
    "categoria": "Fútbol",
    "imagen": "/assets/images/inter-miami-home-2025.webp",
    "createdAt": "2026-01-08T06:27:22.000Z"
  },
  {
    "id": "P00036",
    "nombre": "Inter Milan 2025 Home",
    "descripcion": "Camiseta Inter Milan 2025 versión local",
    "precio": 60,
    "stock": 30,
    "categoryId": "C00004",
    "categoria": "Fútbol",
    "imagen": "/assets/images/inter-milan-2025-home.webp",
    "createdAt": "2026-01-08T06:27:22.000Z"
  },
  {
    "id": "P00037",
    "nombre": "Japon 2025 Home",
    "descripcion": "Camiseta selección Japón 2025 versión local",
    "precio": 60,
    "stock": 30,
    "categoryId": "C00004",
    "categoria": "Fútbol",
    "imagen": "/assets/images/japon-2025-home.webp",
    "createdAt": "2026-01-08T06:27:22.000Z"
  },
  {
    "id": "P00038",
    "nombre": "Juventus 2025 Away",
    "descripcion": "Camiseta Juventus 2025 versión visitante",
    "precio": 60,
    "stock": 30,
    "categoryId": "C00004",
    "categoria": "Fútbol",
    "imagen": "/assets/images/juventus-2025-away.webp",
    "createdAt": "2026-01-08T06:27:22.000Z"
  },
  {
    "id": "P00039",
    "nombre": "Juventus 2026 Local",
    "descripcion": "Camiseta Juventus 2026 versión local",
    "precio": 60,
    "stock": 30,
    "categoryId": "C00004",
    "categoria": "Fútbol",
    "imagen": "/assets/images/juventus-2026-local.webp",
    "createdAt": "2026-01-08T06:27:22.000Z"
  },
  {
    "id": "P00040",
    "nombre": "Leverkusen 2026 Home",
    "descripcion": "Camiseta Bayer Leverkusen 2026 versión local",
    "precio": 60,
    "stock": 30,
    "categoryId": "C00004",
    "categoria": "Fútbol",
    "imagen": "/assets/images/leverkusen-2026-home.webp",
    "createdAt": "2026-01-08T06:27:22.000Z"
  },
  {
    "id": "P00041",
    "nombre": "Liverpool 2026 Local",
    "descripcion": "Camiseta Liverpool 2026 versión local",
    "precio": 60,
    "stock": 30,
    "categoryId": "C00004",
    "categoria": "Fútbol",
    "imagen": "/assets/images/liverpool-2026-local.webp",
    "createdAt": "2026-01-08T06:27:22.000Z"
  },
  {
    "id": "P00042",
    "nombre": "Liverpool Home 2025",
    "descripcion": "Camiseta Liverpool 2025 versión local",
    "precio": 60,
    "stock": 30,
    "categoryId": "C00004",
    "categoria": "Fútbol",
    "imagen": "/assets/images/liverpool-home-2025.webp",
    "createdAt": "2026-01-08T06:27:22.000Z"
  },
  {
    "id": "P00044",
    "nombre": "Manchester City 2025 Away",
    "descripcion": "Camiseta Manchester City 2025 versión visitante",
    "precio": 60,
    "stock": 30,
    "categoryId": "C00004",
    "categoria": "Fútbol",
    "imagen": "/assets/images/manchester-city-2025-away.webp",
    "createdAt": "2026-01-08T06:27:22.000Z"
  },
  {
    "id": "P00045",
    "nombre": "Manchester City 2026 Local",
    "descripcion": "Camiseta Manchester City 2026 versión local",
    "precio": 60,
    "stock": 30,
    "categoryId": "C00004",
    "categoria": "Fútbol",
    "imagen": "/assets/images/manchester-city-2026-local.webp",
    "createdAt": "2026-01-08T06:27:22.000Z"
  },
  {
    "id": "P00046",
    "nombre": "Manchester United 2007 Local Retro",
    "descripcion": "Camiseta retro Manchester United 2007 versión local",
    "precio": 45,
    "stock": 25,
    "categoryId": "C00004",
    "categoria": "Fútbol",
    "imagen": "/assets/images/manchester-united-2007-local-retro.webp",
    "createdAt": "2026-01-08T06:27:22.000Z"
  },
  {
    "id": "P00047",
    "nombre": "Manchester United 2011 Tercera Retro",
    "descripcion": "Camiseta retro Manchester United 2011 tercera equipación",
    "precio": 45,
    "stock": 25,
    "categoryId": "C00004",
    "categoria": "Fútbol",
    "imagen": "/assets/images/manchester-united-2011-tercera-retro.webp",
    "createdAt": "2026-01-08T06:27:22.000Z"
  },
  {
    "id": "P00048",
    "nombre": "Manchester United 2025 Away",
    "descripcion": "Camiseta Manchester United 2025 versión visitante",
    "precio": 60,
    "stock": 30,
    "categoryId": "C00004",
    "categoria": "Fútbol",
    "imagen": "/assets/images/manchester-united-2025-away.webp",
    "createdAt": "2026-01-08T06:27:22.000Z"
  },
  {
    "id": "P00049",
    "nombre": "Manchester United 2026 Local",
    "descripcion": "Camiseta Manchester United 2026 versión local",
    "precio": 60,
    "stock": 30,
    "categoryId": "C00004",
    "categoria": "Fútbol",
    "imagen": "/assets/images/manchester-united-2026-local.webp",
    "createdAt": "2026-01-08T06:27:22.000Z"
  },
  {
    "id": "P00050",
    "nombre": "Marseille 2025 Home",
    "descripcion": "Camiseta Olympique Marseille 2025 versión local",
    "precio": 60,
    "stock": 30,
    "categoryId": "C00004",
    "categoria": "Fútbol",
    "imagen": "/assets/images/marseille-2025-home.webp",
    "createdAt": "2026-01-08T06:27:22.000Z"
  },
  {
    "id": "P00051",
    "nombre": "Monaco 2025 Home",
    "descripcion": "Camiseta AS Monaco 2025 versión local",
    "precio": 60,
    "stock": 30,
    "categoryId": "C00004",
    "categoria": "Fútbol",
    "imagen": "/assets/images/monaco-2025-home.webp",
    "createdAt": "2026-01-08T06:27:22.000Z"
  },
  {
    "id": "P00052",
    "nombre": "Napoli 2025 Away",
    "descripcion": "Camiseta Napoli 2025 versión visitante",
    "precio": 60,
    "stock": 30,
    "categoryId": "C00004",
    "categoria": "Fútbol",
    "imagen": "/assets/images/napoli-2025-away.webp",
    "createdAt": "2026-01-08T06:27:22.000Z"
  },
  {
    "id": "P00053",
    "nombre": "Portugal 2004 Local Retro",
    "descripcion": "Camiseta retro selección Portugal 2004 versión local",
    "precio": 45,
    "stock": 25,
    "categoryId": "C00004",
    "categoria": "Fútbol",
    "imagen": "/assets/images/portugal-2004-local-retro.webp",
    "createdAt": "2026-01-08T06:27:22.000Z"
  },
  {
    "id": "P00054",
    "nombre": "Portugal 2025 Home",
    "descripcion": "Camiseta selección Portugal 2025 versión local",
    "precio": 60,
    "stock": 30,
    "categoryId": "C00004",
    "categoria": "Fútbol",
    "imagen": "/assets/images/portugal-2025-home.webp",
    "createdAt": "2026-01-08T06:27:22.000Z"
  },
  {
    "id": "P00055",
    "nombre": "Psg 2026 Local",
    "descripcion": "Camiseta Paris Saint-Germain 2026 versión local",
    "precio": 60,
    "stock": 30,
    "categoryId": "C00004",
    "categoria": "Fútbol",
    "imagen": "/assets/images/psg-2026-local.webp",
    "createdAt": "2026-01-08T06:27:22.000Z"
  },
  {
    "id": "P00056",
    "nombre": "Real Betis 2025 Home",
    "descripcion": "Camiseta Real Betis 2025 versión local",
    "precio": 60,
    "stock": 30,
    "categoryId": "C00004",
    "categoria": "Fútbol",
    "imagen": "/assets/images/real-betis-2025-home.webp",
    "createdAt": "2026-01-08T06:27:22.000Z"
  },
  {
    "id": "P00057",
    "nombre": "Real Madrid 2015 Tercera Retro",
    "descripcion": "Camiseta retro Real Madrid 2015 tercera equipación",
    "precio": 45,
    "stock": 25,
    "categoryId": "C00004",
    "categoria": "Fútbol",
    "imagen": "/assets/images/real-madrid-2015-tercera-retro.webp",
    "createdAt": "2026-01-08T06:27:22.000Z"
  },
  {
    "id": "P00058",
    "nombre": "Real Madrid 2017 Local Retro",
    "descripcion": "Camiseta retro Real Madrid 2017 versión local",
    "precio": 45,
    "stock": 25,
    "categoryId": "C00004",
    "categoria": "Fútbol",
    "imagen": "/assets/images/real-madrid-2017-local-retro.webp",
    "createdAt": "2026-01-08T06:27:22.000Z"
  },
  {
    "id": "P00059",
    "nombre": "Real Madrid 2025 Local",
    "descripcion": "Camiseta Real Madrid 2025 versión local",
    "precio": 60,
    "stock": 30,
    "categoryId": "C00004",
    "categoria": "Fútbol",
    "imagen": "/assets/images/real-madrid-2025-local.webp",
    "createdAt": "2026-01-08T06:27:22.000Z"
  },
  {
    "id": "P00060",
    "nombre": "Roma 2025 Home",
    "descripcion": "Camiseta AS Roma 2025 versión local",
    "precio": 60,
    "stock": 30,
    "categoryId": "C00004",
    "categoria": "Fútbol",
    "imagen": "/assets/images/roma-2025-home.webp",
    "createdAt": "2026-01-08T06:27:22.000Z"
  },
  {
    "id": "P00062",
    "nombre": "Aucas 2025 Home Ecuador",
    "descripcion": "Camiseta Aucas 2025 versión local Ecuador",
    "precio": 55,
    "stock": 30,
    "categoryId": "C00004",
    "categoria": "Fútbol",
    "imagen": "/assets/images/aucas-2025-home-ecuador.webp",
    "createdAt": "2026-01-08T06:27:22.000Z"
  },
  {
    "id": "P00063",
    "nombre": "Barcelona Ecuador 2025 Home",
    "descripcion": "Camiseta Barcelona SC Ecuador 2025 versión local",
    "precio": 55,
    "stock": 30,
    "categoryId": "C00004",
    "categoria": "Fútbol",
    "imagen": "/assets/images/barcelona-ecuador-2025-home.webp",
    "createdAt": "2026-01-08T06:27:22.000Z"
  },
  {
    "id": "P00064",
    "nombre": "Colombia 2024 Third",
    "descripcion": "Camiseta selección Colombia 2024 tercera equipación",
    "precio": 60,
    "stock": 25,
    "categoryId": "C00004",
    "categoria": "Fútbol",
    "imagen": "/assets/images/colombia-2024-third.webp",
    "createdAt": "2026-01-08T06:27:22.000Z"
  },
  {
    "id": "P94238",
    "nombre": "America 2026 local",
    "descripcion": "Local 2026",
    "precio": 50,
    "stock": 15,
    "categoryId": "C00004",
    "categoria": "Fútbol",
    "imagen": "/assets/images/america-2026-local.webp",
    "createdAt": "2026-01-08T06:27:22.000Z"
  },
  {
    "id": "P00068",
    "nombre": "Ferrari F1 Team 2025",
    "descripcion": "Jersey Ferrari F1 Team temporada 2025",
    "precio": 85,
    "stock": 20,
    "categoryId": "C00005",
    "categoria": "Fórmula 1",
    "imagen": "/assets/images/ferrari-f1-team-2025.webp",
    "createdAt": "2026-01-08T06:27:22.000Z"
  },
  {
    "id": "P00069",
    "nombre": "Lewis Hamilton Ferrari 2025",
    "descripcion": "Jersey Ferrari F1 de Lewis Hamilton temporada 2025",
    "precio": 90,
    "stock": 20,
    "categoryId": "C00005",
    "categoria": "Fórmula 1",
    "imagen": "/assets/images/lewis-hamilton-ferrari-2025.webp",
    "createdAt": "2026-01-08T06:27:22.000Z"
  },
  {
    "id": "P00070",
    "nombre": "Charles Leclerc Monaco GP",
    "descripcion": "Jersey Ferrari F1 de Charles Leclerc en el GP de Mónaco",
    "precio": 95,
    "stock": 20,
    "categoryId": "C00005",
    "categoria": "Fórmula 1",
    "imagen": "/assets/images/charles-leclerc-monaco-gp.webp",
    "createdAt": "2026-01-08T06:27:22.000Z"
  },
  {
    "id": "P00071",
    "nombre": "Red Bull Racing 2025",
    "descripcion": "Jersey Red Bull Racing temporada 2025",
    "precio": 85,
    "stock": 20,
    "categoryId": "C00005",
    "categoria": "Fórmula 1",
    "imagen": "/assets/images/red-bull-racing-2025.webp",
    "createdAt": "2026-01-08T06:27:22.000Z"
  },
  {
    "id": "P00076",
    "nombre": "Williams Racing 2025",
    "descripcion": "Jersey Williams Racing temporada 2025",
    "precio": 65,
    "stock": 20,
    "categoryId": "C00005",
    "categoria": "Fórmula 1",
    "imagen": "/assets/images/williams-racing-2025.webp",
    "createdAt": "2026-01-08T06:27:22.000Z"
  },
  {
    "id": "P00077",
    "nombre": "Haas F1 Team 2025",
    "descripcion": "Jersey Haas F1 Team temporada 2025",
    "precio": 60,
    "stock": 20,
    "categoryId": "C00005",
    "categoria": "Fórmula 1",
    "imagen": "/assets/images/haas-f1-team-2025.webp",
    "createdAt": "2026-01-08T06:27:22.000Z"
  },
  {
    "id": "P00080",
    "nombre": "Buzo Compresión Hombre Jersey Club",
    "descripcion": "Buzo de compresión para hombre de la marca Jersey Club",
    "precio": 35,
    "stock": 18,
    "categoryId": "C00007",
    "categoria": "Jersey Club Brand",
    "imagen": "/assets/images/buzo-compresion-hombre-jersey-club.webp",
    "createdAt": "2026-01-08T06:27:22.000Z"
  },
  {
    "id": "P00081",
    "nombre": "Camiseta Deportiva Hombre Jersey Club",
    "descripcion": "Camiseta deportiva para hombre de la marca Jersey Club",
    "precio": 28,
    "stock": 19,
    "categoryId": "C00007",
    "categoria": "Jersey Club Brand",
    "imagen": "/assets/images/camiseta-deportiva-hombre-jersey-club.webp",
    "createdAt": "2026-01-08T06:27:22.000Z"
  },
  {
    "id": "P00082",
    "nombre": "Camiseta Deportiva Mujer Jersey Club",
    "descripcion": "Camiseta deportiva para mujer de la marca Jersey Club",
    "precio": 28,
    "stock": 20,
    "categoryId": "C00007",
    "categoria": "Jersey Club Brand",
    "imagen": "/assets/images/camiseta-deportiva-mujer-jersey-club.webp",
    "createdAt": "2026-01-08T06:27:22.000Z"
  },
  {
    "id": "P00083",
    "nombre": "Gorra Running Jersey Club",
    "descripcion": "Gorra para running de la marca Jersey Club",
    "precio": 18,
    "stock": 20,
    "categoryId": "C00007",
    "categoria": "Jersey Club Brand",
    "imagen": "/assets/images/gorra-running-jersey-club.webp",
    "createdAt": "2026-01-08T06:27:22.000Z"
  },
  {
    "id": "P00084",
    "nombre": "Medias Running Jersey Club",
    "descripcion": "Medias para running de la marca Jersey Club",
    "precio": 12,
    "stock": 20,
    "categoryId": "C00007",
    "categoria": "Jersey Club Brand",
    "imagen": "/assets/images/medias-running-jersey-club.webp",
    "createdAt": "2026-01-08T06:27:22.000Z"
  },
  {
    "id": "P00085",
    "nombre": "Pantaloneta Deportiva Hombre Jersey Club",
    "descripcion": "Pantaloneta deportiva para hombre de la marca Jersey Club",
    "precio": 22,
    "stock": 20,
    "categoryId": "C00007",
    "categoria": "Jersey Club Brand",
    "imagen": "/assets/images/pantaloneta-deportiva-hombre-jersey-club.webp",
    "createdAt": "2026-01-08T06:27:22.000Z"
  },
  {
    "id": "P00086",
    "nombre": "Pantaloneta Running Hombre Jersey Club",
    "descripcion": "Pantaloneta para running de la marca Jersey Club",
    "precio": 25,
    "stock": 20,
    "categoryId": "C00007",
    "categoria": "Jersey Club Brand",
    "imagen": "/assets/images/pantaloneta-running-hombre-jersey-club.webp",
    "createdAt": "2026-01-08T06:27:22.000Z"
  },
  {
    "id": "P73364",
    "nombre": "America 2025 local",
    "descripcion": "america",
    "precio": 80,
    "stock": 15,
    "categoryId": "C00004",
    "categoria": "Fútbol",
    "imagen": "/assets/images/america-2025-visitante.webp",
    "createdAt": "2026-01-08T06:46:14.008Z"
  }
]